{ "height":40,
 "layers":[
        {
         "data":[0, 0, 0, 0, 0, 0, 0, 21, 21, 21, 21, 21, 21, 21, 21, 21, 21, 21, 21, 21, 21, 21, 21, 21, 21, 21, 21, 21, 21, 21, 21, 0, 0, 0, 0, 0, 0, 0, 0, 0, 0, 0, 0, 0, 0, 0, 0, 21, 21, 0, 0, 0, 0, 0, 0, 0, 0, 0, 21, 21, 21, 21, 21, 21, 24, 0, 0, 0, 0, 0, 21, 22, 0, 0, 0, 0, 0, 0, 0, 0, 0, 0, 0, 0, 0, 0, 23, 21, 24, 0, 0, 0, 0, 0, 0, 0, 0, 0, 0, 0, 0, 0, 0, 0, 0, 0, 44, 44, 0, 0, 63, 21, 0, 0, 0, 0, 0, 0, 0, 0, 0, 0, 0, 0, 0, 0, 21, 21, 0, 0, 0, 0, 0, 0, 0, 0, 0, 0, 0, 0, 0, 0, 0, 23, 21, 0, 0, 0, 0, 21, 21, 24, 0, 0, 0, 0, 0, 0, 0, 0, 0, 0, 0, 0, 0, 0, 21, 21, 21, 21, 21, 21, 21, 21, 22, 0, 0, 0, 0, 0, 0, 23, 21, 21, 21, 21, 21, 21, 21, 24, 0, 0, 0, 0, 23, 21, 21, 22, 0, 0, 0, 0, 0, 0, 0, 0, 0, 0, 0, 0, 0, 0, 0, 0, 0, 21, 21, 21, 21, 22, 0, 0, 21, 0, 0, 0, 0, 0, 0, 0, 0, 0, 0, 0, 21, 21, 21, 21, 22, 0, 0, 0, 0, 0, 0, 0, 0, 0, 0, 0, 0, 0, 0, 0, 0, 0, 0, 0, 21, 21, 21, 0, 21, 21, 0, 0, 0, 0, 0, 0, 0, 0, 0, 0, 21, 0, 0, 25, 21, 0, 0, 0, 0, 0, 0, 0, 0, 0, 0, 0, 0, 0, 0, 0, 0, 0, 0, 0, 0, 21, 21, 0, 21, 21, 21, 0, 0, 0, 0, 0, 0, 0, 0, 0, 21, 0, 0, 0, 21, 0, 0, 0, 0, 0, 0, 0, 0, 0, 0, 0, 0, 0, 0, 0, 0, 0, 0, 0, 0, 21, 21, 0, 25, 21, 21, 0, 0, 0, 0, 0, 0, 0, 0, 0, 21, 0, 23, 21, 21, 21, 0, 0, 0, 0, 0, 0, 0, 0, 0, 0, 0, 0, 0, 0, 0, 0, 0, 0, 23, 21, 24, 0, 0, 25, 21, 21, 21, 0, 0, 0, 0, 0, 0, 0, 21, 0, 21, 21, 21, 21, 0, 0, 0, 0, 0, 0, 0, 0, 0, 0, 0, 0, 0, 0, 0, 0, 0, 23, 24, 0, 0, 0, 0, 0, 0, 25, 21, 21, 21, 0, 0, 0, 0, 0, 21, 0, 21, 21, 0, 0, 0, 0, 0, 0, 0, 0, 0, 0, 0, 0, 0, 0, 0, 0, 23, 21, 21, 24, 0, 0, 0, 0, 0, 0, 0, 0, 0, 25, 21, 21, 21, 21, 21, 21, 24, 0, 21, 21, 0, 0, 0, 0, 0, 0, 0, 0, 0, 0, 0, 0, 0, 0, 0, 0, 21, 24, 0, 0, 0, 0, 0, 0, 0, 0, 0, 0, 0, 0, 0, 25, 21, 21, 21, 24, 0, 0, 21, 21, 0, 0, 0, 0, 0, 0, 0, 0, 0, 0, 0, 0, 0, 0, 0, 23, 24, 0, 0, 0, 0, 0, 0, 0, 0, 0, 0, 0, 0, 0, 0, 0, 0, 0, 0, 0, 0, 0, 21, 21, 0, 0, 0, 0, 0, 0, 0, 0, 0, 23, 21, 21, 21, 21, 24, 0, 0, 0, 0, 0, 23, 21, 21, 0, 0, 0, 0, 0, 44, 44, 0, 0, 0, 0, 0, 0, 0, 23, 21, 24, 0, 0, 0, 0, 0, 0, 0, 0, 0, 21, 24, 0, 0, 0, 0, 0, 0, 0, 0, 0, 21, 21, 21, 0, 0, 0, 0, 44, 44, 44, 44, 0, 0, 23, 21, 21, 21, 21, 0, 0, 0, 0, 0, 0, 0, 0, 0, 0, 0, 21, 0, 0, 0, 0, 0, 0, 0, 0, 0, 23, 21, 21, 21, 0, 0, 0, 0, 44, 44, 44, 44, 0, 0, 21, 21, 21, 21, 24, 0, 0, 0, 0, 0, 0, 0, 0, 0, 0, 0, 21, 0, 0, 0, 0, 0, 0, 0, 0, 0, 21, 21, 21, 21, 0, 0, 0, 0, 0, 44, 44, 0, 0, 0, 21, 21, 0, 0, 0, 0, 0, 0, 0, 0, 0, 0, 0, 0, 0, 0, 21, 0, 0, 0, 0, 0, 0, 0, 0, 0, 21, 21, 21, 21, 0, 0, 0, 0, 0, 0, 0, 0, 0, 0, 25, 21, 0, 0, 0, 0, 0, 0, 0, 0, 0, 0, 0, 0, 0, 0, 21, 0, 0, 0, 0, 0, 0, 0, 0, 0, 21, 21, 21, 21, 0, 0, 0, 0, 0, 0, 0, 0, 0, 0, 0, 25, 21, 0, 0, 0, 0, 23, 0, 0, 0, 0, 0, 0, 0, 0, 21, 0, 0, 0, 0, 0, 0, 0, 0, 0, 21, 21, 21, 21, 0, 0, 0, 23, 21, 21, 21, 21, 22, 0, 0, 0, 21, 0, 0, 0, 0, 21, 21, 0, 0, 0, 0, 0, 0, 0, 21, 0, 0, 0, 0, 0, 0, 0, 0, 0, 25, 21, 21, 21, 21, 21, 21, 21, 21, 21, 21, 25, 21, 22, 0, 0, 25, 21, 0, 0, 0, 21, 21, 0, 0, 0, 0, 0, 0, 0, 21, 0, 0, 0, 0, 0, 0, 0, 0, 0, 0, 25, 21, 21, 21, 21, 21, 21, 21, 21, 21, 21, 25, 21, 0, 0, 0, 21, 21, 0, 0, 21, 21, 0, 0, 0, 0, 0, 0, 0, 21, 0, 0, 0, 0, 0, 0, 0, 0, 0, 0, 0, 25, 21, 21, 21, 22, 21, 21, 21, 21, 21, 21, 21, 0, 0, 0, 25, 21, 21, 21, 21, 21, 0, 0, 0, 0, 0, 0, 23, 24, 0, 0, 0, 0, 0, 0, 0, 0, 0, 0, 0, 0, 0, 0, 21, 21, 21, 21, 21, 21, 21, 21, 21, 0, 0, 0, 0, 25, 21, 21, 21, 21, 0, 0, 0, 0, 0, 0, 21, 0, 0, 0, 0, 0, 0, 0, 0, 0, 0, 0, 0, 0, 0, 0, 0, 21, 21, 21, 21, 21, 21, 21, 21, 0, 0, 44, 0, 0, 0, 0, 21, 21, 0, 0, 0, 23, 21, 21, 24, 0, 0, 0, 0, 0, 0, 0, 0, 0, 0, 0, 0, 0, 0, 0, 0, 21, 22, 21, 21, 21, 21, 21, 21, 0, 0, 44, 44, 0, 0, 0, 21, 21, 0, 0, 0, 21, 0, 0, 0, 0, 0, 0, 0, 0, 0, 0, 0, 0, 0, 0, 0, 0, 0, 0, 0, 25, 21, 22, 21, 21, 21, 21, 21, 21, 0, 0, 44, 0, 0, 23, 21, 21, 0, 0, 0, 21, 0, 0, 0, 0, 0, 0, 0, 0, 0, 0, 0, 0, 0, 0, 0, 0, 0, 0, 0, 0, 25, 21, 22, 21, 21, 21, 21, 21, 0, 0, 0, 0, 23, 21, 24, 0, 0, 0, 0, 21, 0, 0, 0, 0, 44, 44, 0, 0, 0, 0, 0, 0, 0, 0, 0, 0, 0, 0, 0, 0, 0, 25, 21, 21, 21, 21, 21, 21, 0, 0, 23, 21, 21, 24, 0, 0, 0, 0, 0, 21, 0, 0, 0, 0, 44, 44, 44, 44, 0, 0, 0, 0, 0, 0, 0, 0, 0, 0, 0, 0, 0, 0, 0, 25, 21, 21, 21, 21, 21, 21, 21, 21, 24, 0, 0, 0, 0, 0, 0, 21, 0, 0, 0, 0, 44, 44, 44, 44, 0, 0, 0, 0, 0, 0, 0, 0, 0, 0, 0, 0, 0, 0, 0, 0, 0, 25, 21, 21, 21, 21, 24, 0, 0, 0, 0, 0, 0, 0, 0, 21, 0, 0, 0, 0, 0, 44, 44, 0, 0, 0, 0, 0, 0, 0, 0, 0, 0, 0, 0, 0, 0, 0, 0, 0, 0, 0, 21, 21, 0, 0, 0, 0, 0, 0, 0, 0, 0, 0, 0, 21, 0, 0, 0, 0, 0, 0, 0, 0, 0, 0, 0, 0, 0, 0, 0, 0, 0, 0, 0, 0, 0, 0, 0, 0, 0, 0, 21, 21, 0, 0, 0, 0, 0, 0, 0, 0, 0, 0, 23, 24, 0, 0, 0, 0, 0, 0, 0, 0, 0, 0, 0, 0, 0, 0, 0, 0, 0, 0, 0, 0, 0, 0, 0, 0, 0, 0, 21, 21, 0, 0, 0, 0, 0, 0, 0, 0, 0, 0, 21, 0, 0, 0, 0, 0, 0, 0, 0, 0, 0, 0, 0, 0, 0, 0, 0, 0, 0, 0, 0, 0, 23, 21, 21, 21, 21, 21, 21, 24, 0, 0, 0, 0, 0, 0, 0, 0, 0, 0, 21, 0, 0, 0, 0, 0, 0, 0, 0, 0, 0, 0, 0, 0, 0, 0, 0, 0, 0, 0, 0, 23, 21, 24, 0, 21, 21, 21, 24, 0, 0, 0, 0, 0, 0, 0, 0, 0, 0, 0, 21, 21, 21, 21, 21, 21, 21, 21, 21, 21, 21, 21, 21, 21, 21, 21, 21, 11, 21, 21, 21, 21, 21, 0, 0, 0, 0, 0, 0, 0, 0, 0, 0, 0, 0, 0, 0, 0, 0, 0, 0, 0, 0, 0, 0, 0, 0, 0, 0, 0, 0, 0, 0, 0, 0, 0, 21, 11, 21, 0, 0, 0, 0, 0, 0, 0, 0, 0, 0, 0, 0, 0, 0, 0, 0, 0, 0, 0, 0, 0, 0, 0, 0, 0, 0, 0, 0, 0, 0, 0, 0, 0, 0, 0, 0, 0, 21, 11, 21, 0, 0, 0, 0, 0, 0, 0, 0, 0, 0, 0, 0, 0, 0, 0, 0, 0, 0, 0],
         "height":40,
         "name":"base",
         "opacity":1,
         "type":"tilelayer",
         "visible":true,
         "width":40,
         "x":0,
         "y":0
        }, 
        {
         "height":40,
         "name":"bugs",
         "objects":[
                {
                 "gid":61,
                 "height":0,
                 "name":"",
                 "properties":
                    {

                    },
                 "type":"",
                 "visible":true,
                 "width":0,
                 "x":353,
                 "y":96
                }, 
                {
                 "gid":61,
                 "height":0,
                 "name":"",
                 "properties":
                    {

                    },
                 "type":"",
                 "visible":true,
                 "width":0,
                 "x":768,
                 "y":416
                }, 
                {
                 "gid":61,
                 "height":0,
                 "name":"",
                 "properties":
                    {

                    },
                 "type":"",
                 "visible":true,
                 "width":0,
                 "x":545,
                 "y":449
                }, 
                {
                 "gid":61,
                 "height":0,
                 "name":"",
                 "properties":
                    {

                    },
                 "type":"",
                 "visible":true,
                 "width":0,
                 "x":321,
                 "y":543
                }, 
                {
                 "gid":61,
                 "height":0,
                 "name":"",
                 "properties":
                    {

                    },
                 "type":"",
                 "visible":true,
                 "width":0,
                 "x":352,
                 "y":641
                }, 
                {
                 "gid":61,
                 "height":0,
                 "name":"",
                 "properties":
                    {

                    },
                 "type":"",
                 "visible":true,
                 "width":0,
                 "x":320,
                 "y":832
                }, 
                {
                 "gid":61,
                 "height":0,
                 "name":"",
                 "properties":
                    {

                    },
                 "type":"",
                 "visible":true,
                 "width":0,
                 "x":640,
                 "y":896
                }, 
                {
                 "gid":61,
                 "height":0,
                 "name":"",
                 "properties":
                    {

                    },
                 "type":"",
                 "visible":true,
                 "width":0,
                 "x":1024,
                 "y":769
                }, 
                {
                 "gid":61,
                 "height":0,
                 "name":"",
                 "properties":
                    {

                    },
                 "type":"",
                 "visible":true,
                 "width":0,
                 "x":192,
                 "y":1088
                }],
         "opacity":1,
         "type":"objectgroup",
         "visible":true,
         "width":40,
         "x":0,
         "y":0
        }],
 "orientation":"orthogonal",
 "properties":
    {

    },
 "tileheight":32,
 "tilesets":[
        {
         "firstgid":1,
         "image":"..\/..\/..\/grunt-free\/assets\/tiles.png",
         "imageheight":320,
         "imagewidth":320,
         "margin":0,
         "name":"tiles",
         "properties":
            {

            },
         "spacing":0,
         "tileheight":32,
         "tilewidth":32
        }],
 "tilewidth":32,
 "version":1,
 "width":40
}